conclave/__init__.py
conclave/after_scenario.py
conclave/before_scenario.py
conclave/color.py
conclave/custom_keywords.py
conclave/dependency.html
conclave/dependency_graph.py
conclave/feedback.py
conclave/feedback_adapter.py
conclave/feedback_schema.py
conclave/helpers.py
conclave/junit_report.py
conclave/mermaid.min.js
conclave/monitor.html
conclave/monitor.py
conclave/report.html
conclave/report.min.js
conclave/report.py
conclave/scenario.py
conclave/scenario_context.py
conclave/scenario_result.py
conclave/scenario_scope.py
conclave/step.py
conclave/step_definition.py
conclave/step_result.py
conclave/task.py
conclave/task_logger.py
conclave/task_monitor.py
conclave/task_runner.py
conclave/task_runner_config.py
conclave/template_base.py
conclave/testresult_info.py
conclave/timeline.html
conclave/timeline.py
conclave/vis-timeline-graph2d.min.css
conclave/vis-timeline-graph2d.min.js
conclave/world.py
paraworld-1.6.2.dist-info/LICENSE.txt
paraworld-1.6.2.dist-info/METADATA
paraworld-1.6.2.dist-info/WHEEL
paraworld-1.6.2.dist-info/top_level.txt
paraworld-1.6.2.dist-info/RECORD
