Metadata-Version: 2.1
Name: paraworld
Version: 1.6.2
Summary: A BDD framework for running parallel and concurrent tests
Home-page: https://github.com/DasAng/paraworld
Download-URL: http://pypi.python.org/pypi/paraworld
Author: DasAng
Author-email: 
License: MIT
Keywords: gherkin,parallel,bdd
Platform: any
Classifier: Programming Language :: Python
Classifier: Programming Language :: Python :: 3
License-File: LICENSE.txt
Requires-Dist: gherkin-official (==22.0.0)
Requires-Dist: jinja2 (==3.0.2)
Requires-Dist: psutil (==5.8.0)
Requires-Dist: requests (==2.26.0)
